[
  {
    "comp_id": "C007",
    "op_type": "detach",
    "tool_id": "T_impact",
    "symptom": "OVER_TORQUE_NO_ADVANCE",
    "signals": {
      "force": 89.8,
      "torque": 95.8,
      "over_torque": 1
    },
    "context": {
      "value_piece": 15,
      "no_destroy": false,
      "alt_paths": false
    },
    "history": {
      "failure_count": 1
    }
  },
  {
    "comp_id": "C014",
    "op_type": "cut",
    "tool_id": "T_torx",
    "symptom": "OVER_TORQUE_NO_ADVANCE",
    "signals": {
      "force": 77.6,
      "torque": 64.4,
      "over_torque": 1
    },
    "context": {
      "value_piece": 15,
      "no_destroy": false,
      "alt_paths": false
    },
    "history": {
      "failure_count": 3
    }
  },
  {
    "comp_id": "C011",
    "op_type": "detach",
    "tool_id": "T_hex",
    "symptom": "NO_SEPARATION",
    "signals": {
      "force": 80.4,
      "torque": 70.0,
      "joint_opened": 0
    },
    "context": {
      "value_piece": 32,
      "no_destroy": false,
      "alt_paths": false
    },
    "history": {
      "failure_count": 2
    }
  },
  {
    "comp_id": "C003",
    "op_type": "cut",
    "tool_id": "T_impact",
    "symptom": "OVER_TORQUE_NO_ADVANCE",
    "signals": {
      "force": 75.1,
      "torque": 71.7,
      "over_torque": 1
    },
    "context": {
      "value_piece": 29,
      "no_destroy": false,
      "alt_paths": false,
      "alt_tools_available": [
        "T_pneumatic"
      ]
    },
    "history": {
      "failure_count": 3
    }
  }
]