{
  "nodes": [
    {
      "id": "C000",
      "profit": 28,
      "cost": 1,
      "duration": 118,
      "milp_index": 1
    },
    {
      "id": "C001",
      "profit": 23,
      "cost": 7,
      "duration": 200,
      "milp_index": 2
    },
    {
      "id": "C002",
      "profit": 24,
      "cost": 2,
      "duration": 140,
      "milp_index": 3
    },
    {
      "id": "C003",
      "profit": 23,
      "cost": 9,
      "duration": 272,
      "milp_index": 4
    },
    {
      "id": "C004",
      "profit": 29,
      "cost": 3,
      "duration": 64,
      "milp_index": 5
    },
    {
      "id": "C005",
      "profit": 22,
      "cost": 1,
      "duration": 48,
      "milp_index": 6
    },
    {
      "id": "C006",
      "profit": 25,
      "cost": 3,
      "duration": 133,
      "milp_index": 7
    },
    {
      "id": "C007",
      "profit": 28,
      "cost": 8,
      "duration": 48,
      "milp_index": 8
    },
    {
      "id": "C008",
      "profit": 20,
      "cost": 2,
      "duration": 131,
      "milp_index": 9
    },
    {
      "id": "C009",
      "profit": 21,
      "cost": 5,
      "duration": 137,
      "milp_index": 10
    },
    {
      "id": "C010",
      "profit": 27,
      "cost": 10,
      "duration": 189,
      "milp_index": 11
    },
    {
      "id": "C011",
      "profit": 24,
      "cost": 3,
      "duration": 145,
      "milp_index": 12
    },
    {
      "id": "C012",
      "profit": 22,
      "cost": 9,
      "duration": 209,
      "milp_index": 13
    },
    {
      "id": "C013",
      "profit": 20,
      "cost": 10,
      "duration": 211,
      "milp_index": 14
    },
    {
      "id": "C014",
      "profit": 27,
      "cost": 3,
      "duration": 166,
      "milp_index": 15
    },
    {
      "id": "C015",
      "profit": 24,
      "cost": 2,
      "duration": 73,
      "milp_index": 16
    },
    {
      "id": "C016",
      "profit": 28,
      "cost": 9,
      "duration": 137,
      "milp_index": 17
    },
    {
      "id": "C017",
      "profit": 22,
      "cost": 10,
      "duration": 117,
      "milp_index": 18
    },
    {
      "id": "C018",
      "profit": 20,
      "cost": 6,
      "duration": 83,
      "milp_index": 19
    },
    {
      "id": "C019",
      "profit": 23,
      "cost": 2,
      "duration": 62,
      "milp_index": 20
    },
    {
      "id": "C020",
      "profit": 27,
      "cost": 5,
      "duration": 89,
      "milp_index": 21
    },
    {
      "id": "C021",
      "profit": 22,
      "cost": 8,
      "duration": 163,
      "milp_index": 22
    },
    {
      "id": "C022",
      "profit": 27,
      "cost": 3,
      "duration": 97,
      "milp_index": 23
    },
    {
      "id": "C023",
      "profit": 25,
      "cost": 9,
      "duration": 103,
      "milp_index": 24
    },
    {
      "id": "C024",
      "profit": 20,
      "cost": 8,
      "duration": 84,
      "milp_index": 25
    },
    {
      "id": "C025",
      "profit": 26,
      "cost": 5,
      "duration": 69,
      "milp_index": 26
    },
    {
      "id": "C026",
      "profit": 24,
      "cost": 2,
      "duration": 123,
      "milp_index": 27
    },
    {
      "id": "C027",
      "profit": 25,
      "cost": 2,
      "duration": 72,
      "milp_index": 28
    },
    {
      "id": "C028",
      "profit": 28,
      "cost": 4,
      "duration": 163,
      "milp_index": 29
    },
    {
      "id": "C029",
      "profit": 27,
      "cost": 10,
      "duration": 101,
      "milp_index": 30
    },
    {
      "id": "C030",
      "profit": 27,
      "cost": 7,
      "duration": 89,
      "milp_index": 31
    },
    {
      "id": "C031",
      "profit": 22,
      "cost": 9,
      "duration": 59,
      "milp_index": 32
    },
    {
      "id": "C032",
      "profit": 21,
      "cost": 1,
      "duration": 196,
      "milp_index": 33
    },
    {
      "id": "C033",
      "profit": 30,
      "cost": 7,
      "duration": 35,
      "milp_index": 34
    },
    {
      "id": "C034",
      "profit": 21,
      "cost": 7,
      "duration": 68,
      "milp_index": 35
    },
    {
      "id": "C035",
      "profit": 28,
      "cost": 2,
      "duration": 70,
      "milp_index": 36
    },
    {
      "id": "C036",
      "profit": 27,
      "cost": 10,
      "duration": 84,
      "milp_index": 37
    },
    {
      "id": "C037",
      "profit": 27,
      "cost": 2,
      "duration": 184,
      "milp_index": 38
    },
    {
      "id": "C038",
      "profit": 27,
      "cost": 6,
      "duration": 168,
      "milp_index": 39
    },
    {
      "id": "C039",
      "profit": 25,
      "cost": 7,
      "duration": 106,
      "milp_index": 40
    },
    {
      "id": "C040",
      "profit": 29,
      "cost": 7,
      "duration": 179,
      "milp_index": 41
    },
    {
      "id": "C041",
      "profit": 24,
      "cost": 2,
      "duration": 205,
      "milp_index": 42
    },
    {
      "id": "C042",
      "profit": 25,
      "cost": 9,
      "duration": 105,
      "milp_index": 43
    },
    {
      "id": "C043",
      "profit": 22,
      "cost": 7,
      "duration": 84,
      "milp_index": 44
    },
    {
      "id": "C044",
      "profit": 26,
      "cost": 5,
      "duration": 144,
      "milp_index": 45
    },
    {
      "id": "C045",
      "profit": 30,
      "cost": 2,
      "duration": 146,
      "milp_index": 46
    },
    {
      "id": "C046",
      "profit": 25,
      "cost": 6,
      "duration": 138,
      "milp_index": 47
    },
    {
      "id": "C047",
      "profit": 26,
      "cost": 5,
      "duration": 44,
      "milp_index": 48
    },
    {
      "id": "C048",
      "profit": 29,
      "cost": 8,
      "duration": 29,
      "milp_index": 49
    },
    {
      "id": "C049",
      "profit": 23,
      "cost": 3,
      "duration": 145,
      "milp_index": 50
    },
    {
      "id": "C050",
      "profit": 28,
      "cost": 6,
      "duration": 92,
      "milp_index": 51
    },
    {
      "id": "C051",
      "profit": 26,
      "cost": 5,
      "duration": 89,
      "milp_index": 52
    },
    {
      "id": "C052",
      "profit": 21,
      "cost": 9,
      "duration": 200,
      "milp_index": 53
    },
    {
      "id": "C053",
      "profit": 24,
      "cost": 6,
      "duration": 24,
      "milp_index": 54
    },
    {
      "id": "C054",
      "profit": 27,
      "cost": 4,
      "duration": 256,
      "milp_index": 55
    },
    {
      "id": "C055",
      "profit": 27,
      "cost": 1,
      "duration": 33,
      "milp_index": 56
    },
    {
      "id": "C056",
      "profit": 30,
      "cost": 6,
      "duration": 122,
      "milp_index": 57
    },
    {
      "id": "C057",
      "profit": 24,
      "cost": 3,
      "duration": 48,
      "milp_index": 58
    },
    {
      "id": "C058",
      "profit": 22,
      "cost": 1,
      "duration": 278,
      "milp_index": 59
    },
    {
      "id": "C059",
      "profit": 26,
      "cost": 6,
      "duration": 125,
      "milp_index": 60
    },
    {
      "id": "C060",
      "profit": 28,
      "cost": 4,
      "duration": 256,
      "milp_index": 61
    },
    {
      "id": "C061",
      "profit": 29,
      "cost": 3,
      "duration": 96,
      "milp_index": 62
    },
    {
      "id": "C062",
      "profit": 28,
      "cost": 10,
      "duration": 342,
      "milp_index": 63
    },
    {
      "id": "C063",
      "profit": 24,
      "cost": 6,
      "duration": 26,
      "milp_index": 64
    },
    {
      "id": "C064",
      "profit": 28,
      "cost": 8,
      "duration": 75,
      "milp_index": 65
    },
    {
      "id": "C065",
      "profit": 23,
      "cost": 10,
      "duration": 87,
      "milp_index": 66
    },
    {
      "id": "C066",
      "profit": 27,
      "cost": 8,
      "duration": 99,
      "milp_index": 67
    },
    {
      "id": "C067",
      "profit": 24,
      "cost": 2,
      "duration": 158,
      "milp_index": 68
    },
    {
      "id": "C068",
      "profit": 23,
      "cost": 2,
      "duration": 183,
      "milp_index": 69
    },
    {
      "id": "C069",
      "profit": 25,
      "cost": 6,
      "duration": 150,
      "milp_index": 70
    },
    {
      "id": "C070",
      "profit": 24,
      "cost": 4,
      "duration": 131,
      "milp_index": 71
    },
    {
      "id": "C071",
      "profit": 24,
      "cost": 3,
      "duration": 107,
      "milp_index": 72
    },
    {
      "id": "C072",
      "profit": 29,
      "cost": 2,
      "duration": 23,
      "milp_index": 73
    },
    {
      "id": "C073",
      "profit": 25,
      "cost": 7,
      "duration": 312,
      "milp_index": 74
    },
    {
      "id": "C074",
      "profit": 26,
      "cost": 8,
      "duration": 201,
      "milp_index": 75
    },
    {
      "id": "C075",
      "profit": 25,
      "cost": 2,
      "duration": 37,
      "milp_index": 76
    },
    {
      "id": "C076",
      "profit": 27,
      "cost": 6,
      "duration": 191,
      "milp_index": 77
    },
    {
      "id": "C077",
      "profit": 30,
      "cost": 2,
      "duration": 131,
      "milp_index": 78
    },
    {
      "id": "C078",
      "profit": 26,
      "cost": 8,
      "duration": 274,
      "milp_index": 79
    },
    {
      "id": "C079",
      "profit": 27,
      "cost": 4,
      "duration": 59,
      "milp_index": 80
    },
    {
      "id": "C080",
      "profit": 28,
      "cost": 1,
      "duration": 111,
      "milp_index": 81
    },
    {
      "id": "C081",
      "profit": 26,
      "cost": 8,
      "duration": 348,
      "milp_index": 82
    },
    {
      "id": "C082",
      "profit": 28,
      "cost": 3,
      "duration": 222,
      "milp_index": 83
    },
    {
      "id": "C083",
      "profit": 23,
      "cost": 5,
      "duration": 22,
      "milp_index": 84
    },
    {
      "id": "C084",
      "profit": 22,
      "cost": 4,
      "duration": 65,
      "milp_index": 85
    },
    {
      "id": "C085",
      "profit": 26,
      "cost": 1,
      "duration": 201,
      "milp_index": 86
    },
    {
      "id": "C086",
      "profit": 29,
      "cost": 3,
      "duration": 27,
      "milp_index": 87
    },
    {
      "id": "C087",
      "profit": 24,
      "cost": 3,
      "duration": 58,
      "milp_index": 88
    },
    {
      "id": "C088",
      "profit": 30,
      "cost": 2,
      "duration": 199,
      "milp_index": 89
    },
    {
      "id": "C089",
      "profit": 29,
      "cost": 1,
      "duration": 156,
      "milp_index": 90
    },
    {
      "id": "C090",
      "profit": 24,
      "cost": 2,
      "duration": 49,
      "milp_index": 91
    },
    {
      "id": "C091",
      "profit": 29,
      "cost": 10,
      "duration": 107,
      "milp_index": 92
    },
    {
      "id": "C092",
      "profit": 21,
      "cost": 8,
      "duration": 109,
      "milp_index": 93
    },
    {
      "id": "C093",
      "profit": 23,
      "cost": 8,
      "duration": 33,
      "milp_index": 94
    },
    {
      "id": "C094",
      "profit": 26,
      "cost": 10,
      "duration": 178,
      "milp_index": 95
    },
    {
      "id": "C095",
      "profit": 20,
      "cost": 10,
      "duration": 93,
      "milp_index": 96
    },
    {
      "id": "C096",
      "profit": 26,
      "cost": 4,
      "duration": 152,
      "milp_index": 97
    },
    {
      "id": "C097",
      "profit": 29,
      "cost": 5,
      "duration": 38,
      "milp_index": 98
    },
    {
      "id": "C098",
      "profit": 21,
      "cost": 3,
      "duration": 55,
      "milp_index": 99
    },
    {
      "id": "C099",
      "profit": 22,
      "cost": 6,
      "duration": 80,
      "milp_index": 100
    }
  ],
  "edges": [
    [
      "C000",
      "C023"
    ],
    [
      "C001",
      "C040"
    ],
    [
      "C002",
      "C040"
    ],
    [
      "C003",
      "C040"
    ],
    [
      "C004",
      "C040"
    ],
    [
      "C005",
      "C018"
    ],
    [
      "C005",
      "C019"
    ],
    [
      "C005",
      "C030"
    ],
    [
      "C006",
      "C010"
    ],
    [
      "C006",
      "C013"
    ],
    [
      "C006",
      "C015"
    ],
    [
      "C006",
      "C020"
    ],
    [
      "C006",
      "C021"
    ],
    [
      "C007",
      "C011"
    ],
    [
      "C008",
      "C012"
    ],
    [
      "C008",
      "C017"
    ],
    [
      "C008",
      "C021"
    ],
    [
      "C008",
      "C022"
    ],
    [
      "C009",
      "C014"
    ],
    [
      "C009",
      "C016"
    ],
    [
      "C010",
      "C023"
    ],
    [
      "C011",
      "C023"
    ],
    [
      "C012",
      "C023"
    ],
    [
      "C013",
      "C023"
    ],
    [
      "C014",
      "C023"
    ],
    [
      "C015",
      "C040"
    ],
    [
      "C016",
      "C040"
    ],
    [
      "C017",
      "C040"
    ],
    [
      "C018",
      "C040"
    ],
    [
      "C019",
      "C029"
    ],
    [
      "C020",
      "C024"
    ],
    [
      "C020",
      "C025"
    ],
    [
      "C020",
      "C027"
    ],
    [
      "C020",
      "C028"
    ],
    [
      "C020",
      "C032"
    ],
    [
      "C021",
      "C026"
    ],
    [
      "C021",
      "C031"
    ],
    [
      "C022",
      "C030"
    ],
    [
      "C022",
      "C033"
    ],
    [
      "C023",
      "C034"
    ],
    [
      "C023",
      "C035"
    ],
    [
      "C023",
      "C036"
    ],
    [
      "C023",
      "C037"
    ],
    [
      "C023",
      "C038"
    ],
    [
      "C023",
      "C039"
    ],
    [
      "C023",
      "C045"
    ],
    [
      "C024",
      "C040"
    ],
    [
      "C025",
      "C040"
    ],
    [
      "C026",
      "C040"
    ],
    [
      "C027",
      "C041"
    ],
    [
      "C028",
      "C042"
    ],
    [
      "C029",
      "C044"
    ],
    [
      "C030",
      "C043"
    ],
    [
      "C030",
      "C068"
    ],
    [
      "C032",
      "C046"
    ],
    [
      "C032",
      "C061"
    ],
    [
      "C033",
      "C070"
    ],
    [
      "C034",
      "C079"
    ],
    [
      "C040",
      "C047"
    ],
    [
      "C040",
      "C048"
    ],
    [
      "C040",
      "C049"
    ],
    [
      "C040",
      "C050"
    ],
    [
      "C040",
      "C051"
    ],
    [
      "C040",
      "C052"
    ],
    [
      "C040",
      "C053"
    ],
    [
      "C041",
      "C054"
    ],
    [
      "C042",
      "C056"
    ],
    [
      "C043",
      "C055"
    ],
    [
      "C046",
      "C057"
    ],
    [
      "C047",
      "C059"
    ],
    [
      "C047",
      "C096"
    ],
    [
      "C049",
      "C063"
    ],
    [
      "C049",
      "C071"
    ],
    [
      "C051",
      "C097"
    ],
    [
      "C052",
      "C061"
    ],
    [
      "C053",
      "C076"
    ],
    [
      "C054",
      "C058"
    ],
    [
      "C055",
      "C060"
    ],
    [
      "C057",
      "C062"
    ],
    [
      "C058",
      "C064"
    ],
    [
      "C059",
      "C065"
    ],
    [
      "C060",
      "C066"
    ],
    [
      "C061",
      "C069"
    ],
    [
      "C062",
      "C067"
    ],
    [
      "C062",
      "C068"
    ],
    [
      "C062",
      "C070"
    ],
    [
      "C062",
      "C071"
    ],
    [
      "C064",
      "C072"
    ],
    [
      "C065",
      "C073"
    ],
    [
      "C067",
      "C074"
    ],
    [
      "C069",
      "C076"
    ],
    [
      "C070",
      "C075"
    ],
    [
      "C070",
      "C077"
    ],
    [
      "C072",
      "C078"
    ],
    [
      "C073",
      "C079"
    ],
    [
      "C074",
      "C080"
    ],
    [
      "C075",
      "C081"
    ],
    [
      "C075",
      "C082"
    ],
    [
      "C075",
      "C083"
    ],
    [
      "C078",
      "C086"
    ],
    [
      "C079",
      "C084"
    ],
    [
      "C079",
      "C087"
    ],
    [
      "C079",
      "C098"
    ],
    [
      "C080",
      "C085"
    ],
    [
      "C080",
      "C089"
    ],
    [
      "C081",
      "C090"
    ],
    [
      "C083",
      "C088"
    ],
    [
      "C084",
      "C091"
    ],
    [
      "C085",
      "C092"
    ],
    [
      "C086",
      "C094"
    ],
    [
      "C087",
      "C093"
    ],
    [
      "C088",
      "C095"
    ],
    [
      "C089",
      "C096"
    ],
    [
      "C091",
      "C097"
    ],
    [
      "C092",
      "C098"
    ],
    [
      "C093",
      "C097"
    ],
    [
      "C095",
      "C099"
    ]
  ],
  "targets": [
    "C071",
    "C050",
    "C036"
  ],
  "order_rules": [
    {
      "if": [
        "C000",
        "C023"
      ],
      "condition": "C000 avant C023"
    },
    {
      "if": [
        "C001",
        "C040"
      ],
      "condition": "C001 avant C040"
    },
    {
      "if": [
        "C002",
        "C040"
      ],
      "condition": "C002 avant C040"
    },
    {
      "if": [
        "C003",
        "C040"
      ],
      "condition": "C003 avant C040"
    },
    {
      "if": [
        "C004",
        "C040"
      ],
      "condition": "C004 avant C040"
    },
    {
      "if": [
        "C005",
        "C018"
      ],
      "condition": "C005 avant C018"
    },
    {
      "if": [
        "C005",
        "C019"
      ],
      "condition": "C005 avant C019"
    },
    {
      "if": [
        "C005",
        "C030"
      ],
      "condition": "C005 avant C030"
    },
    {
      "if": [
        "C006",
        "C010"
      ],
      "condition": "C006 avant C010"
    },
    {
      "if": [
        "C006",
        "C013"
      ],
      "condition": "C006 avant C013"
    },
    {
      "if": [
        "C006",
        "C015"
      ],
      "condition": "C006 avant C015"
    },
    {
      "if": [
        "C006",
        "C020"
      ],
      "condition": "C006 avant C020"
    },
    {
      "if": [
        "C006",
        "C021"
      ],
      "condition": "C006 avant C021"
    },
    {
      "if": [
        "C007",
        "C011"
      ],
      "condition": "C007 avant C011"
    },
    {
      "if": [
        "C008",
        "C012"
      ],
      "condition": "C008 avant C012"
    },
    {
      "if": [
        "C008",
        "C017"
      ],
      "condition": "C008 avant C017"
    },
    {
      "if": [
        "C008",
        "C021"
      ],
      "condition": "C008 avant C021"
    },
    {
      "if": [
        "C008",
        "C022"
      ],
      "condition": "C008 avant C022"
    },
    {
      "if": [
        "C009",
        "C014"
      ],
      "condition": "C009 avant C014"
    },
    {
      "if": [
        "C009",
        "C016"
      ],
      "condition": "C009 avant C016"
    },
    {
      "if": [
        "C010",
        "C023"
      ],
      "condition": "C010 avant C023"
    },
    {
      "if": [
        "C011",
        "C023"
      ],
      "condition": "C011 avant C023"
    },
    {
      "if": [
        "C012",
        "C023"
      ],
      "condition": "C012 avant C023"
    },
    {
      "if": [
        "C013",
        "C023"
      ],
      "condition": "C013 avant C023"
    },
    {
      "if": [
        "C014",
        "C023"
      ],
      "condition": "C014 avant C023"
    },
    {
      "if": [
        "C015",
        "C040"
      ],
      "condition": "C015 avant C040"
    },
    {
      "if": [
        "C016",
        "C040"
      ],
      "condition": "C016 avant C040"
    },
    {
      "if": [
        "C017",
        "C040"
      ],
      "condition": "C017 avant C040"
    },
    {
      "if": [
        "C018",
        "C040"
      ],
      "condition": "C018 avant C040"
    },
    {
      "if": [
        "C019",
        "C029"
      ],
      "condition": "C019 avant C029"
    },
    {
      "if": [
        "C020",
        "C024"
      ],
      "condition": "C020 avant C024"
    },
    {
      "if": [
        "C020",
        "C025"
      ],
      "condition": "C020 avant C025"
    },
    {
      "if": [
        "C020",
        "C027"
      ],
      "condition": "C020 avant C027"
    },
    {
      "if": [
        "C020",
        "C028"
      ],
      "condition": "C020 avant C028"
    },
    {
      "if": [
        "C020",
        "C032"
      ],
      "condition": "C020 avant C032"
    },
    {
      "if": [
        "C021",
        "C026"
      ],
      "condition": "C021 avant C026"
    },
    {
      "if": [
        "C021",
        "C031"
      ],
      "condition": "C021 avant C031"
    },
    {
      "if": [
        "C022",
        "C030"
      ],
      "condition": "C022 avant C030"
    },
    {
      "if": [
        "C022",
        "C033"
      ],
      "condition": "C022 avant C033"
    },
    {
      "if": [
        "C023",
        "C034"
      ],
      "condition": "C023 avant C034"
    },
    {
      "if": [
        "C023",
        "C035"
      ],
      "condition": "C023 avant C035"
    },
    {
      "if": [
        "C023",
        "C036"
      ],
      "condition": "C023 avant C036"
    },
    {
      "if": [
        "C023",
        "C037"
      ],
      "condition": "C023 avant C037"
    },
    {
      "if": [
        "C023",
        "C038"
      ],
      "condition": "C023 avant C038"
    },
    {
      "if": [
        "C023",
        "C039"
      ],
      "condition": "C023 avant C039"
    },
    {
      "if": [
        "C023",
        "C045"
      ],
      "condition": "C023 avant C045"
    },
    {
      "if": [
        "C024",
        "C040"
      ],
      "condition": "C024 avant C040"
    },
    {
      "if": [
        "C025",
        "C040"
      ],
      "condition": "C025 avant C040"
    },
    {
      "if": [
        "C026",
        "C040"
      ],
      "condition": "C026 avant C040"
    },
    {
      "if": [
        "C027",
        "C041"
      ],
      "condition": "C027 avant C041"
    },
    {
      "if": [
        "C028",
        "C042"
      ],
      "condition": "C028 avant C042"
    },
    {
      "if": [
        "C029",
        "C044"
      ],
      "condition": "C029 avant C044"
    },
    {
      "if": [
        "C030",
        "C043"
      ],
      "condition": "C030 avant C043"
    },
    {
      "if": [
        "C030",
        "C068"
      ],
      "condition": "C030 avant C068"
    },
    {
      "if": [
        "C032",
        "C046"
      ],
      "condition": "C032 avant C046"
    },
    {
      "if": [
        "C032",
        "C061"
      ],
      "condition": "C032 avant C061"
    },
    {
      "if": [
        "C033",
        "C070"
      ],
      "condition": "C033 avant C070"
    },
    {
      "if": [
        "C034",
        "C079"
      ],
      "condition": "C034 avant C079"
    },
    {
      "if": [
        "C040",
        "C047"
      ],
      "condition": "C040 avant C047"
    },
    {
      "if": [
        "C040",
        "C048"
      ],
      "condition": "C040 avant C048"
    },
    {
      "if": [
        "C040",
        "C049"
      ],
      "condition": "C040 avant C049"
    },
    {
      "if": [
        "C040",
        "C050"
      ],
      "condition": "C040 avant C050"
    },
    {
      "if": [
        "C040",
        "C051"
      ],
      "condition": "C040 avant C051"
    },
    {
      "if": [
        "C040",
        "C052"
      ],
      "condition": "C040 avant C052"
    },
    {
      "if": [
        "C040",
        "C053"
      ],
      "condition": "C040 avant C053"
    },
    {
      "if": [
        "C041",
        "C054"
      ],
      "condition": "C041 avant C054"
    },
    {
      "if": [
        "C042",
        "C056"
      ],
      "condition": "C042 avant C056"
    },
    {
      "if": [
        "C043",
        "C055"
      ],
      "condition": "C043 avant C055"
    },
    {
      "if": [
        "C046",
        "C057"
      ],
      "condition": "C046 avant C057"
    },
    {
      "if": [
        "C047",
        "C059"
      ],
      "condition": "C047 avant C059"
    },
    {
      "if": [
        "C047",
        "C096"
      ],
      "condition": "C047 avant C096"
    },
    {
      "if": [
        "C049",
        "C063"
      ],
      "condition": "C049 avant C063"
    },
    {
      "if": [
        "C049",
        "C071"
      ],
      "condition": "C049 avant C071"
    },
    {
      "if": [
        "C051",
        "C097"
      ],
      "condition": "C051 avant C097"
    },
    {
      "if": [
        "C052",
        "C061"
      ],
      "condition": "C052 avant C061"
    },
    {
      "if": [
        "C053",
        "C076"
      ],
      "condition": "C053 avant C076"
    },
    {
      "if": [
        "C054",
        "C058"
      ],
      "condition": "C054 avant C058"
    },
    {
      "if": [
        "C055",
        "C060"
      ],
      "condition": "C055 avant C060"
    },
    {
      "if": [
        "C057",
        "C062"
      ],
      "condition": "C057 avant C062"
    },
    {
      "if": [
        "C058",
        "C064"
      ],
      "condition": "C058 avant C064"
    },
    {
      "if": [
        "C059",
        "C065"
      ],
      "condition": "C059 avant C065"
    },
    {
      "if": [
        "C060",
        "C066"
      ],
      "condition": "C060 avant C066"
    },
    {
      "if": [
        "C061",
        "C069"
      ],
      "condition": "C061 avant C069"
    },
    {
      "if": [
        "C062",
        "C067"
      ],
      "condition": "C062 avant C067"
    },
    {
      "if": [
        "C062",
        "C068"
      ],
      "condition": "C062 avant C068"
    },
    {
      "if": [
        "C062",
        "C070"
      ],
      "condition": "C062 avant C070"
    },
    {
      "if": [
        "C062",
        "C071"
      ],
      "condition": "C062 avant C071"
    },
    {
      "if": [
        "C064",
        "C072"
      ],
      "condition": "C064 avant C072"
    },
    {
      "if": [
        "C065",
        "C073"
      ],
      "condition": "C065 avant C073"
    },
    {
      "if": [
        "C067",
        "C074"
      ],
      "condition": "C067 avant C074"
    },
    {
      "if": [
        "C069",
        "C076"
      ],
      "condition": "C069 avant C076"
    },
    {
      "if": [
        "C070",
        "C075"
      ],
      "condition": "C070 avant C075"
    },
    {
      "if": [
        "C070",
        "C077"
      ],
      "condition": "C070 avant C077"
    },
    {
      "if": [
        "C072",
        "C078"
      ],
      "condition": "C072 avant C078"
    },
    {
      "if": [
        "C073",
        "C079"
      ],
      "condition": "C073 avant C079"
    },
    {
      "if": [
        "C074",
        "C080"
      ],
      "condition": "C074 avant C080"
    },
    {
      "if": [
        "C075",
        "C081"
      ],
      "condition": "C075 avant C081"
    },
    {
      "if": [
        "C075",
        "C082"
      ],
      "condition": "C075 avant C082"
    },
    {
      "if": [
        "C075",
        "C083"
      ],
      "condition": "C075 avant C083"
    },
    {
      "if": [
        "C078",
        "C086"
      ],
      "condition": "C078 avant C086"
    },
    {
      "if": [
        "C079",
        "C084"
      ],
      "condition": "C079 avant C084"
    },
    {
      "if": [
        "C079",
        "C087"
      ],
      "condition": "C079 avant C087"
    },
    {
      "if": [
        "C079",
        "C098"
      ],
      "condition": "C079 avant C098"
    },
    {
      "if": [
        "C080",
        "C085"
      ],
      "condition": "C080 avant C085"
    },
    {
      "if": [
        "C080",
        "C089"
      ],
      "condition": "C080 avant C089"
    },
    {
      "if": [
        "C081",
        "C090"
      ],
      "condition": "C081 avant C090"
    },
    {
      "if": [
        "C083",
        "C088"
      ],
      "condition": "C083 avant C088"
    },
    {
      "if": [
        "C084",
        "C091"
      ],
      "condition": "C084 avant C091"
    },
    {
      "if": [
        "C085",
        "C092"
      ],
      "condition": "C085 avant C092"
    },
    {
      "if": [
        "C086",
        "C094"
      ],
      "condition": "C086 avant C094"
    },
    {
      "if": [
        "C087",
        "C093"
      ],
      "condition": "C087 avant C093"
    },
    {
      "if": [
        "C088",
        "C095"
      ],
      "condition": "C088 avant C095"
    },
    {
      "if": [
        "C089",
        "C096"
      ],
      "condition": "C089 avant C096"
    },
    {
      "if": [
        "C091",
        "C097"
      ],
      "condition": "C091 avant C097"
    },
    {
      "if": [
        "C092",
        "C098"
      ],
      "condition": "C092 avant C098"
    },
    {
      "if": [
        "C093",
        "C097"
      ],
      "condition": "C093 avant C097"
    },
    {
      "if": [
        "C095",
        "C099"
      ],
      "condition": "C095 avant C099"
    }
  ]
}